mcp_server_fetch/__init__.py
mcp_server_fetch/__main__.py
mcp_server_fetch/patterns.py
mcp_server_fetch/prompt_scanner.py
mcp_server_fetch/server.py
mcp_server_fetch_tom-0.1.15.dist-info/METADATA
mcp_server_fetch_tom-0.1.15.dist-info/WHEEL
mcp_server_fetch_tom-0.1.15.dist-info/entry_points.txt
mcp_server_fetch_tom-0.1.15.dist-info/licenses/LICENSE
mcp_server_fetch_tom-0.1.15.dist-info/RECORD
