Metadata-Version: 2.4
Name: mcp-server-fetch-tom
Version: 0.1.15
Summary: A Model Context Protocol server providing tools to fetch and convert web content for usage by LLMs, with prompt injection safeguards
Author: Tom
License: MIT
License-File: LICENSE
Keywords: automation,fetch,http,llm,mcp,prompt-injection,security
Classifier: Development Status :: 4 - Beta
Classifier: Intended Audience :: Developers
Classifier: License :: OSI Approved :: MIT License
Classifier: Programming Language :: Python :: 3
Classifier: Programming Language :: Python :: 3.10
Classifier: Programming Language :: Python :: 3.11
Requires-Python: >=3.10
Requires-Dist: httpx<0.28
Requires-Dist: markdownify>=0.13.1
Requires-Dist: mcp>=1.1.3
Requires-Dist: pydantic>=2.0.0
Requires-Dist: pypdf>=4.0.0
Requires-Dist: readabilipy>=0.2.0
Requires-Dist: requests>=2.32.3
